{
  "ramya": {
    "success": 0,
    "failed": 1,
    "aborted": 5,
    "last_run": "2025-09-10 12:34:40 IST",
    "executions": [
      {
        "id": "byowU4gRSJ6fMlKG2H4M9A",
        "status": "Failed",
        "end_ts": 1757483226082
      },
      {
        "id": "AGFNJTkmTJySd0sO-hSSMg",
        "status": "Aborted",
        "end_ts": 1757485244488
      },
      {
        "id": "3BXevqeNTLmKAiH_DMqFBQ",
        "status": "Aborted",
        "end_ts": 1757485782756
      },
      {
        "id": "lwrAcKhzTZmNTm44eYjvsQ",
        "status": "Aborted",
        "end_ts": 1757486701430
      },
      {
        "id": "0BjXVSOTTeGB6vsFXwA18Q",
        "status": "Aborted",
        "end_ts": 1757486876918
      },
      {
        "id": "sfdcQ3l8TBCZCK5CcKcYgw",
        "status": "Aborted",
        "end_ts": 1757487880889
      }
    ],
    "last_status": "Aborted"
  },
  "ravi": {
    "success": 0,
    "failed": 0,
    "aborted": 2,
    "last_run": "2025-09-10 15:54:04 IST",
    "executions": [
      {
        "id": "mOETprb0QSu_yTT5kFkm4w",
        "status": "Aborted",
        "end_ts": 1757498448873
      },
      {
        "id": "CYwLBdBRRgSsZYS_D477Iw",
        "status": "Aborted",
        "end_ts": 1757499844820
      }
    ],
    "last_status": "Aborted"
  }
}